Metadata-Version: 2.1
Name: pgman
Version: 0.0.6
Summary: Python操作PostgreSQL
Home-page: https://github.com/markadc/wauo
Author: WangTuo
Author-email: markadc@126.com
License: MIT
Keywords: Python,DB,PostgreSQL
